CHANGES.txt
MANIFEST.in
README.rst
setup.py
isotoma/__init__.py
isotoma.buildout.autodevelop.egg-info/PKG-INFO
isotoma.buildout.autodevelop.egg-info/SOURCES.txt
isotoma.buildout.autodevelop.egg-info/dependency_links.txt
isotoma.buildout.autodevelop.egg-info/entry_points.txt
isotoma.buildout.autodevelop.egg-info/namespace_packages.txt
isotoma.buildout.autodevelop.egg-info/not-zip-safe
isotoma.buildout.autodevelop.egg-info/requires.txt
isotoma.buildout.autodevelop.egg-info/top_level.txt
isotoma/buildout/__init__.py
isotoma/buildout/autodevelop/__init__.py