Metadata-Version: 1.0
Name: isotoma.buildout.autodevelop
Version: 0.0.14
Summary: Buildout extension to automatically develop eggs found in specified directories.
Home-page: http://pypi.python.org/pypi/isotoma.buildout.autodevelop
Author: John Carr
Author-email: john.carr@isotoma.com
License: Apache Software License
Keywords: buildout extension log
Platform: UNKNOWN
Classifier: Framework :: Buildout
Classifier: Intended Audience :: System Administrators
Classifier: Operating System :: POSIX
Classifier: License :: OSI Approved :: Apache Software License
